CHANGELOG.txt
LICENSE.txt
MANIFEST.in
README.txt
requirement.txt
requirements.txt
requirements_2.txt
setup.py
wmseo/__init__.py
wmseo.egg-info/PKG-INFO
wmseo.egg-info/SOURCES.txt
wmseo.egg-info/dependency_links.txt
wmseo.egg-info/top_level.txt