Metadata-Version: 1.1
Name: wmseo
Version: 1.0.2
Summary: SEO Functions from WMC
Home-page: UNKNOWN
Author: Lucas Ximenes
Author-email: UNKNOWN
License: MIT
Keywords: WMCCann
Platform: UNKNOWN
Classifier: Development Status :: 5 - Production/Stable
Classifier: Intended Audience :: Developers
Classifier: Operating System :: Microsoft :: Windows :: Windows 10
Classifier: License :: OSI Approved :: MIT License
Classifier: Programming Language :: Python :: 3
